nextcloud_notes_api/__init__.py
nextcloud_notes_api/api_exceptions.py
nextcloud_notes_api/api_wrapper.py
nextcloud_notes_api/documentation.md
nextcloud_notes_api/note.py
nextcloud_notes_api-1.0.0.dist-info/LICENSE
nextcloud_notes_api-1.0.0.dist-info/WHEEL
nextcloud_notes_api-1.0.0.dist-info/METADATA
nextcloud_notes_api-1.0.0.dist-info/RECORD
