Metadata-Version: 2.1
Name: nextcloud-notes-api
Version: 1.0.0
Summary: A Nextcloud Notes app API wrapper
Home-page: https://github.com/coma64/nextcloud-notes-api
License: MIT
Keywords: nextcloud,notes,api,api-wrapper
Author: coma64
Author-email: coma64@outlook.com
Requires-Python: >=3.7,<4.0
Classifier: License :: OSI Approved :: MIT License
Classifier: Programming Language :: Python :: 3
Classifier: Programming Language :: Python :: 3.7
Classifier: Programming Language :: Python :: 3.8
Classifier: Programming Language :: Python :: 3.9
Requires-Dist: requests-mock (>=1.8.0,<2.0.0)
Project-URL: Documentation, https://coma64.github.io/nextcloud-notes-api/
Project-URL: Repository, https://github.com/coma64/nextcloud-notes-api
